typeboa/__init__.py
typeboa/typeboa.py
typeboa-0.1.1.dist-info/METADATA
typeboa-0.1.1.dist-info/WHEEL
typeboa-0.1.1.dist-info/RECORD
