Metadata-Version: 2.1
Name: typeboa
Version: 0.1.1
Summary: A description of my package.
Author-email: Anish Kanthamneni <akneni@example.com>
License-Expression: MIT
Keywords: one,two
Classifier: License :: OSI Approved :: MIT License
Classifier: Operating System :: OS Independent
Classifier: Programming Language :: Python :: 3
